git_genie/__init__.py
git_genie/main.py
git_genie-0.2.0.dist-info/WHEEL
git_genie-0.2.0.dist-info/entry_points.txt
git_genie-0.2.0.dist-info/METADATA
git_genie-0.2.0.dist-info/RECORD
