Metadata-Version: 2.1
Name: git-genie
Version: 0.2.0
Summary: 
Author: Daniel Palma
Author-email: danivgy@gmail.com
Requires-Python: >=3.10,<4.0
Classifier: Programming Language :: Python :: 3
Classifier: Programming Language :: Python :: 3.10
Classifier: Programming Language :: Python :: 3.11
Requires-Dist: langchain (>=0.0.75,<0.0.76)
Requires-Dist: openai (>=0.26.4,<0.27.0)
Requires-Dist: tiktoken (>=0.1.2,<0.2.0)
Requires-Dist: typer[all] (>=0.7.0,<0.8.0)
